{"inputs":[{"name":"selectBoxValue-selectized","timestamp":"2019-08-23T11:32:12+01:00","value":"","type":"","binding":"shiny.textInput"},{"name":"selectedBynet","timestamp":"2019-08-23T11:28:08+01:00","value":"","type":"","binding":"shiny.selectInput"},{"name":"keypressed","timestamp":"2019-08-23T11:28:09+01:00","value":18,"type":"","binding":""},{"name":"highlightedText","timestamp":"2019-08-23T11:32:12+01:00","value":"","type":"","binding":""},{"name":"selectBoxValue","timestamp":"2019-08-23T11:28:09+01:00","value":"","type":"","binding":"shiny.selectInput"},{"name":"keypressed","timestamp":"2019-08-23T11:28:20+01:00","value":17,"type":"","binding":""},{"name":"net_selectedBy","timestamp":"2019-08-23T11:28:09+01:00","value":"","type":"","binding":""},{"name":"quote","timestamp":"2019-08-23T11:28:09+01:00","value":"","type":"","binding":"shiny.textareaInput"},{"name":"net_selectedBy","timestamp":"2019-08-23T11:28:09+01:00","value":"","type":"","binding":""},{"name":"selectBoxValue","timestamp":"2019-08-23T11:28:09+01:00","value":"","type":"","binding":"shiny.selectInput"},{"name":"net_selectedBy","timestamp":"2019-08-23T11:28:08+01:00","value":"","type":"","binding":""},{"name":"highlightedText","timestamp":"2019-08-23T11:28:08+01:00","value":"","type":"","binding":""},{"name":"keypressed","timestamp":"2019-08-23T11:31:51+01:00","value":18,"type":"","binding":""},{"name":"quote","timestamp":"2019-08-23T11:28:08+01:00","value":"","type":"","binding":"shiny.textareaInput"},{"name":"keypressed","timestamp":"2019-08-23T11:32:12+01:00","value":116,"type":"","binding":""},{"name":"nodeSelectnet","timestamp":"2019-08-23T11:28:08+01:00","value":{},"type":"","binding":"shiny.selectInput"}],"outputs":[{"name":"combo","timestamp":"2019-08-23T11:28:09+01:00","binding":"shiny.htmlOutput"},{"name":"combineLink","timestamp":"2019-08-23T11:28:09+01:00","binding":"shiny.htmlOutput"},{"name":"displayStatementPanel","timestamp":"2019-08-23T11:28:09+01:00","binding":"shiny.htmlOutput"}],"session":[{"app":"causal-mapping","user":"user","server_connected":"2019-08-23T11:27:52+0100","sessionid":"89c931e2e4a5e9f5fee6bc6185f4af01","server_disconnected":"2019-08-23T11:32:13+0100"}]}
