{"inputs":[{"name":"keypressed","timestamp":"2019-08-25T14:25:34+01:00","value":68,"type":"","binding":""},{"name":"function.type","timestamp":"2019-08-25T14:26:13+01:00","value":"+","type":"","binding":"shiny.selectInput"},{"name":"definition.type","timestamp":"2019-08-25T14:26:13+01:00","value":"","type":"","binding":"shiny.selectInput"},{"name":"confidence","timestamp":"2019-08-25T14:25:38+01:00","value":0.5,"type":"","binding":"shiny.sliderInput"},{"name":"selectBoxValue-selectized","timestamp":"2019-08-25T14:26:13+01:00","value":"","type":"","binding":"shiny.textInput"},{"name":"quote","timestamp":"2019-08-25T14:25:29+01:00","value":"","type":"","binding":"shiny.textareaInput"},{"name":"keypressed","timestamp":"2019-08-25T14:25:34+01:00","value":65,"type":"","binding":""},{"name":"selectBoxValue","timestamp":"2019-08-25T14:25:38+01:00","value":"","type":"","binding":"shiny.selectInput"},{"name":"highlightedText","timestamp":"2019-08-25T14:25:35+01:00","value":"","type":"","binding":""},{"name":"quote","timestamp":"2019-08-25T14:25:38+01:00","value":"","type":"","binding":"shiny.textareaInput"},{"name":"selectBoxValue","timestamp":"2019-08-25T14:25:29+01:00","value":"","type":"","binding":"shiny.selectInput"},{"name":"firstuncoded","timestamp":"2019-08-25T14:26:13+01:00","value":0,"type":"shiny.action","binding":"shiny.actionButtonInput"},{"name":"pager__page_current","timestamp":"2019-08-25T14:26:13+01:00","value":1,"type":"shiny.number","binding":"shiny.numberInput"},{"name":"highlightedText","timestamp":"2019-08-25T14:26:01+01:00","value":"","type":"","binding":""},{"name":"highlightedText","timestamp":"2019-08-25T14:25:59+01:00","value":"","type":"","binding":""},{"name":"highlightedText","timestamp":"2019-08-25T14:25:29+01:00","value":"","type":"","binding":""},{"name":"highlightedText","timestamp":"2019-08-25T14:25:34+01:00","value":"","type":"","binding":""},{"name":"pager","timestamp":"2019-08-25T14:25:38+01:00","value":{"page_current":1,"pages_total":{}},"type":"","binding":"oddhypothesis.pageruiInputBinding"},{"name":"keypressed","timestamp":"2019-08-25T14:26:58+01:00","value":116,"type":"","binding":""},{"name":"pager__pages_total","timestamp":"2019-08-25T14:25:38+01:00","value":{},"type":"shiny.number","binding":"shiny.numberInput"},{"name":"arrLabel","timestamp":"2019-08-25T14:26:13+01:00","value":"","type":"","binding":"shiny.textInput"},{"name":"trust","timestamp":"2019-08-25T14:26:13+01:00","value":0.5,"type":"","binding":"shiny.sliderInput"},{"name":"selectBoxValue","timestamp":"2019-08-25T14:26:13+01:00","value":"","type":"","binding":"shiny.selectInput"},{"name":"quote","timestamp":"2019-08-25T14:25:38+01:00","value":"","type":"","binding":"shiny.textareaInput"},{"name":"pager","timestamp":"2019-08-25T14:26:13+01:00","value":{"page_current":1,"pages_total":26},"type":"","binding":"oddhypothesis.pageruiInputBinding"},{"name":"edgeDetails","timestamp":"2019-08-25T14:25:38+01:00","value":false,"type":"","binding":"shiny.checkboxInput"},{"name":"userSelect","timestamp":"2019-08-25T14:26:01+01:00","value":"BSDR","type":"","binding":"shiny.selectInput"},{"name":"confidence","timestamp":"2019-08-25T14:26:13+01:00","value":0.5,"type":"","binding":"shiny.sliderInput"},{"name":"quote","timestamp":"2019-08-25T14:26:14+01:00","value":"","type":"","binding":"shiny.textareaInput"},{"name":"projectSelect","timestamp":"2019-08-25T14:25:29+01:00","value":"","type":"","binding":"shiny.selectInput"},{"name":"selectBoxValue","timestamp":"2019-08-25T14:25:29+01:00","value":"","type":"","binding":"shiny.selectInput"},{"name":"selectBoxValue","timestamp":"2019-08-25T14:25:38+01:00","value":"","type":"","binding":"shiny.selectInput"},{"name":"onlyThisStatement","timestamp":"2019-08-25T14:26:13+01:00","value":true,"type":"","binding":"shiny.checkboxInput"},{"name":"highlightedText","timestamp":"2019-08-25T14:25:34+01:00","value":"","type":"","binding":""},{"name":"overview_col","timestamp":"2019-08-25T14:25:38+01:00","value":0,"type":"shiny.action","binding":"shiny.actionButtonInput"},{"name":"highlightedText","timestamp":"2019-08-25T14:25:37+01:00","value":"","type":"","binding":""},{"name":"strength","timestamp":"2019-08-25T14:26:13+01:00","value":0.5,"type":"","binding":"shiny.sliderInput"},{"name":"overview_col","timestamp":"2019-08-25T14:26:13+01:00","value":0,"type":"shiny.action","binding":"shiny.actionButtonInput"},{"name":"resetSelection","timestamp":"2019-08-25T14:25:38+01:00","value":0,"type":"shiny.action","binding":"shiny.actionButtonInput"},{"name":"highlightedText","timestamp":"2019-08-25T14:26:04+01:00","value":"","type":"","binding":""},{"name":"package","timestamp":"2019-08-25T14:25:38+01:00","value":"","type":"","binding":"shiny.textInput"},{"name":"function.type","timestamp":"2019-08-25T14:25:38+01:00","value":"+","type":"","binding":"shiny.selectInput"},{"name":"highlightedText","timestamp":"2019-08-25T14:25:34+01:00","value":"","type":"","binding":""},{"name":"keypressed","timestamp":"2019-08-25T14:25:34+01:00","value":70,"type":"","binding":""},{"name":"highlightedText","timestamp":"2019-08-25T14:25:34+01:00","value":"","type":"","binding":""},{"name":"definition.type-selectized","timestamp":"2019-08-25T14:26:13+01:00","value":"","type":"","binding":"shiny.textInput"},{"name":"function.type-selectized","timestamp":"2019-08-25T14:26:13+01:00","value":"","type":"","binding":"shiny.textInput"},{"name":"highlightedText","timestamp":"2019-08-25T14:26:04+01:00","value":"","type":"","binding":""},{"name":"highlightedText","timestamp":"2019-08-25T14:26:59+01:00","value":"","type":"","binding":""},{"name":"highlightedText","timestamp":"2019-08-25T14:25:59+01:00","value":"","type":"","binding":""},{"name":"highlightedText","timestamp":"2019-08-25T14:26:08+01:00","value":"","type":"","binding":""},{"name":"highlightedText","timestamp":"2019-08-25T14:25:33+01:00","value":"","type":"","binding":""},{"name":"highlightedText","timestamp":"2019-08-25T14:25:34+01:00","value":"","type":"","binding":""},{"name":"quote","timestamp":"2019-08-25T14:26:13+01:00","value":"","type":"","binding":"shiny.textareaInput"},{"name":"resetSelection","timestamp":"2019-08-25T14:26:13+01:00","value":0,"type":"shiny.action","binding":"shiny.actionButtonInput"},{"name":"selectBoxValue","timestamp":"2019-08-25T14:26:14+01:00","value":"","type":"","binding":"shiny.selectInput"},{"name":"addTo","timestamp":"2019-08-25T14:26:13+01:00","value":0,"type":"shiny.action","binding":"shiny.actionButtonInput"},{"name":"keypressed","timestamp":"2019-08-25T14:25:45+01:00","value":18,"type":"","binding":""},{"name":"pager__page_current","timestamp":"2019-08-25T14:25:38+01:00","value":1,"type":"shiny.number","binding":"shiny.numberInput"},{"name":"trust","timestamp":"2019-08-25T14:25:38+01:00","value":0.5,"type":"","binding":"shiny.sliderInput"},{"name":"strength","timestamp":"2019-08-25T14:25:38+01:00","value":0.5,"type":"","binding":"shiny.sliderInput"},{"name":"highlightedText","timestamp":"2019-08-25T14:25:33+01:00","value":"","type":"","binding":""},{"name":"addFrom","timestamp":"2019-08-25T14:26:13+01:00","value":0,"type":"shiny.action","binding":"shiny.actionButtonInput"},{"name":"highlightedText","timestamp":"2019-08-25T14:25:59+01:00","value":"","type":"","binding":""},{"name":"projectSelect","timestamp":"2019-08-25T14:25:37+01:00","value":"asdf","type":"","binding":"shiny.selectInput"},{"name":"definition.type-selectized","timestamp":"2019-08-25T14:25:38+01:00","value":"","type":"","binding":"shiny.textInput"},{"name":"package","timestamp":"2019-08-25T14:26:13+01:00","value":"","type":"","binding":"shiny.textInput"},{"name":"packageNote","timestamp":"2019-08-25T14:25:38+01:00","value":"","type":"","binding":"shiny.textInput"},{"name":"projectSelect","timestamp":"2019-08-25T14:26:08+01:00","value":"Malawi2","type":"","binding":"shiny.selectInput"},{"name":"selectBoxValue-selectized","timestamp":"2019-08-25T14:25:38+01:00","value":"","type":"","binding":"shiny.textInput"},{"name":"edgeDetails","timestamp":"2019-08-25T14:26:13+01:00","value":false,"type":"","binding":"shiny.checkboxInput"},{"name":"addFrom","timestamp":"2019-08-25T14:25:38+01:00","value":0,"type":"shiny.action","binding":"shiny.actionButtonInput"},{"name":"highlightedText","timestamp":"2019-08-25T14:25:34+01:00","value":"","type":"","binding":""},{"name":"recodeButton","timestamp":"2019-08-25T14:26:13+01:00","value":0,"type":"shiny.action","binding":"shiny.actionButtonInput"},{"name":"definition.type","timestamp":"2019-08-25T14:25:38+01:00","value":"","type":"","binding":"shiny.selectInput"},{"name":"quote","timestamp":"2019-08-25T14:25:29+01:00","value":"","type":"","binding":"shiny.textareaInput"},{"name":"highlightedText","timestamp":"2019-08-25T14:25:34+01:00","value":"","type":"","binding":""},{"name":"onlyThisStatement","timestamp":"2019-08-25T14:25:38+01:00","value":true,"type":"","binding":"shiny.checkboxInput"},{"name":"highlightedText","timestamp":"2019-08-25T14:25:37+01:00","value":"","type":"","binding":""},{"name":"highlightedText","timestamp":"2019-08-25T14:25:33+01:00","value":"","type":"","binding":""},{"name":"recodeButton","timestamp":"2019-08-25T14:25:38+01:00","value":0,"type":"shiny.action","binding":"shiny.actionButtonInput"},{"name":"highlightedText","timestamp":"2019-08-25T14:26:04+01:00","value":"","type":"","binding":""},{"name":"keypressed","timestamp":"2019-08-25T14:25:34+01:00","value":83,"type":"","binding":""},{"name":"net_initialized","timestamp":"2019-08-25T14:26:13+01:00","value":true,"type":"","binding":""},{"name":"projectSelect","timestamp":"2019-08-25T14:26:01+01:00","value":"","type":"","binding":"shiny.selectInput"},{"name":"keypressed","timestamp":"2019-08-25T14:26:22+01:00","value":18,"type":"","binding":""},{"name":"arrLabel","timestamp":"2019-08-25T14:25:38+01:00","value":"","type":"","binding":"shiny.textInput"},{"name":"pager__pages_total","timestamp":"2019-08-25T14:26:13+01:00","value":26,"type":"shiny.number","binding":"shiny.numberInput"},{"name":"firstuncoded","timestamp":"2019-08-25T14:25:38+01:00","value":0,"type":"shiny.action","binding":"shiny.actionButtonInput"},{"name":"function.type-selectized","timestamp":"2019-08-25T14:25:38+01:00","value":"","type":"","binding":"shiny.textInput"},{"name":"packageNote","timestamp":"2019-08-25T14:26:13+01:00","value":"","type":"","binding":"shiny.textInput"},{"name":"highlightedText","timestamp":"2019-08-25T14:26:06+01:00","value":"","type":"","binding":""},{"name":"projectSelect","timestamp":"2019-08-25T14:25:29+01:00","value":"","type":"","binding":"shiny.selectInput"},{"name":"projectSelect","timestamp":"2019-08-25T14:26:01+01:00","value":"","type":"","binding":"shiny.selectInput"},{"name":"addTo","timestamp":"2019-08-25T14:25:38+01:00","value":0,"type":"shiny.action","binding":"shiny.actionButtonInput"}],"outputs":[{"name":"selectBoxButtons","timestamp":"2019-08-25T14:25:38+01:00","binding":"shiny.htmlOutput"},{"name":"combineLink","timestamp":"2019-08-25T14:25:29+01:00","binding":"shiny.htmlOutput"},{"name":"combo","timestamp":"2019-08-25T14:25:29+01:00","binding":"shiny.htmlOutput"},{"name":"pagerBig","timestamp":"2019-08-25T14:25:38+01:00","binding":"shiny.htmlOutput"},{"name":"selectBoxButtons","timestamp":"2019-08-25T14:26:13+01:00","binding":"shiny.htmlOutput"},{"name":"add_edges_widget","timestamp":"2019-08-25T14:26:13+01:00","binding":"shiny.htmlOutput"},{"name":"displayStatementPanel","timestamp":"2019-08-25T14:25:29+01:00","binding":"shiny.htmlOutput"},{"name":"add_edges_widget","timestamp":"2019-08-25T14:25:38+01:00","binding":"shiny.htmlOutput"},{"name":"displayStatementPanel","timestamp":"2019-08-25T14:26:13+01:00","binding":"shiny.htmlOutput"},{"name":"pagerBig","timestamp":"2019-08-25T14:26:13+01:00","binding":"shiny.htmlOutput"},{"name":"net","timestamp":"2019-08-25T14:26:13+01:00","binding":"visNetwork"},{"name":"displayStatementPanel","timestamp":"2019-08-25T14:25:38+01:00","binding":"shiny.htmlOutput"}],"session":[{"app":"causal-mapping","user":"user","server_connected":"2019-08-25T14:25:27+0100","sessionid":"337fd20eae0db7240724ce41a41c0144","server_disconnected":"2019-08-25T14:26:59+0100"}]}
