{"inputs":[{"name":"highlightedText","timestamp":"2019-08-25T20:15:20+01:00","value":"","type":"","binding":""},{"name":"selectBoxValue","timestamp":"2019-08-25T20:15:20+01:00","value":"","type":"","binding":"shiny.selectInput"},{"name":"selectBoxValue","timestamp":"2019-08-25T20:15:20+01:00","value":"","type":"","binding":"shiny.selectInput"},{"name":"quote","timestamp":"2019-08-25T20:15:21+01:00","value":"","type":"","binding":"shiny.textareaInput"},{"name":"quote","timestamp":"2019-08-25T20:15:20+01:00","value":"","type":"","binding":"shiny.textareaInput"},{"name":"projectSelect","timestamp":"2019-08-25T20:15:20+01:00","value":"blank","type":"","binding":"shiny.selectInput"}],"outputs":[{"name":"combineLink","timestamp":"2019-08-25T20:15:20+01:00","binding":"shiny.htmlOutput"},{"name":"displayStatementPanel","timestamp":"2019-08-25T20:15:20+01:00","binding":"shiny.htmlOutput"},{"name":"combo","timestamp":"2019-08-25T20:15:20+01:00","binding":"shiny.htmlOutput"}],"session":[{"app":"causal-mapping","user":"user","server_connected":"2019-08-25T20:15:17+0100","sessionid":"ec8ac1e53b8c70782d0325fa18babcd6","server_disconnected":"2019-08-25T20:15:21+0100"}]}
