{"inputs":[{"name":"highlightedText","timestamp":"2019-08-25T20:38:29+01:00","value":"","type":"","binding":""},{"name":"projectSelect","timestamp":"2019-08-25T20:36:30+01:00","value":"blank","type":"","binding":"shiny.selectInput"},{"name":"selectBoxValue-selectized","timestamp":"2019-08-25T20:38:29+01:00","value":"","type":"","binding":"shiny.textInput"},{"name":"quote","timestamp":"2019-08-25T20:36:30+01:00","value":"","type":"","binding":"shiny.textareaInput"},{"name":"keypressed","timestamp":"2019-08-25T20:38:28+01:00","value":116,"type":"","binding":""},{"name":"highlightedText","timestamp":"2019-08-25T20:39:01+01:00","value":"","type":"","binding":""},{"name":"selectBoxValue","timestamp":"2019-08-25T20:36:30+01:00","value":"","type":"","binding":"shiny.selectInput"},{"name":"keypressed","timestamp":"2019-08-25T20:39:02+01:00","value":18,"type":"","binding":""},{"name":"selectBoxValue","timestamp":"2019-08-25T20:36:30+01:00","value":"","type":"","binding":"shiny.selectInput"},{"name":"highlightedText","timestamp":"2019-08-25T20:36:29+01:00","value":"","type":"","binding":""},{"name":"selectBoxValue-selectized","timestamp":"2019-08-25T20:39:01+01:00","value":"","type":"","binding":"shiny.textInput"},{"name":"quote","timestamp":"2019-08-25T20:36:30+01:00","value":"","type":"","binding":"shiny.textareaInput"}],"session":[{"app":"causal-mapping","user":"user","server_connected":"2019-08-25T20:36:26+0100","sessionid":"67875be55370ca8e5684c3b1c7de5ce4","server_disconnected":"2019-08-25T20:39:13+0100"}]}
