{"inputs":[{"name":"keypressed","timestamp":"2019-09-02T17:06:02+01:00","value":18,"type":"","binding":""},{"name":"highlightedText","timestamp":"2019-09-02T17:06:12+01:00","value":"","type":"","binding":""},{"name":"highlightedText","timestamp":"2019-09-02T17:06:18+01:00","value":"","type":"","binding":""},{"name":"highlightedText","timestamp":"2019-09-02T17:06:08+01:00","value":"","type":"","binding":""},{"name":"keypressed","timestamp":"2019-09-02T17:06:33+01:00","value":116,"type":"","binding":""},{"name":"keypressed","timestamp":"2019-09-02T17:06:19+01:00","value":18,"type":"","binding":""},{"name":"highlightedText","timestamp":"2019-09-02T17:06:08+01:00","value":"","type":"","binding":""},{"name":"highlightedText","timestamp":"2019-09-02T17:06:33+01:00","value":"","type":"","binding":""},{"name":"highlightedText","timestamp":"2019-09-02T17:06:12+01:00","value":"","type":"","binding":""},{"name":"highlightedText","timestamp":"2019-09-02T17:06:19+01:00","value":"","type":"","binding":""},{"name":"highlightedText","timestamp":"2019-09-02T17:06:19+01:00","value":"","type":"","binding":""},{"name":"highlightedText","timestamp":"2019-09-02T17:06:08+01:00","value":"","type":"","binding":""}],"session":[{"app":"causal-mapping","user":"user","server_connected":"2019-09-02T17:05:54+0100","sessionid":"6c963903227764cfa2463c8429bd698d","server_disconnected":"2019-09-02T17:06:34+0100"}]}
